confattr/__init__.py
confattr/config.py
confattr/configfile.py
confattr/formatters.py
confattr/py.typed
confattr/quickstart.py
confattr/runmodule.sh
confattr/state.py
confattr/subprocess_pipe.py
confattr/types.py
confattr/utils.py
confattr-1.7.0.dist-info/licenses/LICENSE
confattr-1.7.0.dist-info/WHEEL
confattr-1.7.0.dist-info/METADATA
confattr-1.7.0.dist-info/RECORD
